jumpmodels/__init__.py
jumpmodels/base.py
jumpmodels/jump.py
jumpmodels/plot.py
jumpmodels/preprocess.py
jumpmodels/sparse_jump.py
jumpmodels/utils/__init__.py
jumpmodels/utils/calculation.py
jumpmodels/utils/cluster.py
jumpmodels/utils/index.py
jumpmodels/utils/validation.py
jumpmodels-0.1.1.dist-info/LICENSE
jumpmodels-0.1.1.dist-info/METADATA
jumpmodels-0.1.1.dist-info/WHEEL
jumpmodels-0.1.1.dist-info/top_level.txt
jumpmodels-0.1.1.dist-info/RECORD
