Metadata-Version: 2.1
Name: jumpmodels
Version: 0.1.1
Summary: Statistical Jump Models in Python, with `scikit-learn`-style APIs
Author-email: Yizhan Shu <olivershu98@gmail.com>
Project-URL: Homepage, https://github.com/Yizhan-Oliver-Shu/jump-models
Project-URL: Issues, https://github.com/Yizhan-Oliver-Shu/jump-models/issues
Keywords: regime,regime switching,jump models,clustering,time series,financial data
Classifier: Programming Language :: Python :: 3
Classifier: License :: OSI Approved :: Apache Software License
Classifier: Operating System :: OS Independent
Classifier: Intended Audience :: Science/Research
Classifier: Intended Audience :: Financial and Insurance Industry
Classifier: Intended Audience :: Developers
Classifier: Topic :: Scientific/Engineering :: Mathematics
Classifier: Topic :: Scientific/Engineering :: Information Analysis
Requires-Python: >=3.8
License-File: LICENSE
Requires-Dist: numpy
Requires-Dist: pandas
Requires-Dist: scipy
Requires-Dist: scikit-learn
Requires-Dist: matplotlib
Provides-Extra: example
Requires-Dist: jupyterlab ; extra == 'example'
Requires-Dist: yfinance ; extra == 'example'
